pamiq_io/__init__.py
pamiq_io/py.typed
pamiq_io/audio/__init__.py
pamiq_io/audio/utils.py
pamiq_io/audio/input/__init__.py
pamiq_io/audio/input/base.py
pamiq_io/audio/input/soundcard.py
pamiq_io/audio/output/__init__.py
pamiq_io/audio/output/base.py
pamiq_io/audio/output/soundcard.py
pamiq_io/keyboard/__init__.py
pamiq_io/keyboard/output/__init__.py
pamiq_io/keyboard/output/base.py
pamiq_io/keyboard/output/inputtino.py
pamiq_io/keyboard/output/windows.py
pamiq_io/mouse/__init__.py
pamiq_io/mouse/output/__init__.py
pamiq_io/mouse/output/base.py
pamiq_io/mouse/output/inputtino.py
pamiq_io/mouse/output/windows.py
pamiq_io/osc/__init__.py
pamiq_io/osc/input.py
pamiq_io/osc/output.py
pamiq_io/video/__init__.py
pamiq_io/video/utils.py
pamiq_io/video/input/__init__.py
pamiq_io/video/input/base.py
pamiq_io/video/input/opencv.py
pamiq_io-0.6.1.dist-info/METADATA
pamiq_io-0.6.1.dist-info/WHEEL
pamiq_io-0.6.1.dist-info/entry_points.txt
pamiq_io-0.6.1.dist-info/licenses/LICENSE
pamiq_io-0.6.1.dist-info/RECORD
