Metadata-Version: 2.4
Name: pamiq-io
Version: 0.6.1
Summary: Versatile I/O library for Python, providing easy access to audio, video, and input device capabilities.
Project-URL: Repository, https://github.com/MLShukai/pamiq-io
Project-URL: Issues, https://github.com/MLShukai/pamiq-io/issues
Author-email: Geson-anko <59220704+Geson-anko@users.noreply.github.com>
License-File: LICENSE
Keywords: AI,Agent,IO,ML,Machine Learning,OBS,audio,automation,inputtino,keyboard,mouse,obs-studio,osc,video
Classifier: Development Status :: 3 - Alpha
Classifier: Intended Audience :: Developers
Classifier: Intended Audience :: Science/Research
Classifier: License :: OSI Approved :: MIT License
Classifier: Natural Language :: English
Classifier: Natural Language :: Japanese
Classifier: Operating System :: MacOS
Classifier: Operating System :: Microsoft :: Windows
Classifier: Operating System :: POSIX :: Linux
Classifier: Programming Language :: Python
Classifier: Programming Language :: Python :: 3
Classifier: Programming Language :: Python :: 3.12
Classifier: Programming Language :: Python :: 3.13
Classifier: Programming Language :: Python :: 3.14
Requires-Python: >=3.12
Provides-Extra: demo
Requires-Dist: pillow>=11.1.0; extra == 'demo'
Requires-Dist: soundfile>=0.13.1; extra == 'demo'
Provides-Extra: inputtino
Requires-Dist: inputtino-python>=0.1.0; (sys_platform == 'linux') and extra == 'inputtino'
Provides-Extra: opencv
Requires-Dist: opencv-python>=4.11.0.86; extra == 'opencv'
Provides-Extra: osc
Requires-Dist: python-osc>=1.9.3; extra == 'osc'
Provides-Extra: soundcard
Requires-Dist: soundcard>=0.4.4; extra == 'soundcard'
Provides-Extra: windows
Requires-Dist: pydirectinput>=1.0.4; (sys_platform == 'win32') and extra == 'windows'
